LICENSE
MANIFEST.in
README.md
pyproject.toml
setup.cfg
setup.py
commons/__init__.py
commons/admin.py
commons/apps.py
commons/models.py
commons/tests.py
commons/views.py
commons/contexts/__init__.py
commons/contexts/build_info.py
commons/db/__init__.py
commons/db/models.py
commons/enumarate/__init__.py
commons/enumarate/enum_base.py
commons/enumarate/enumerates.py
commons/migrations/__init__.py
commons/python/__init__.py
commons/python/decorators.py
commons/python/enumerate.py
commons/python/formatter.py
commons/python/helper.py
commons/python/smtp.py
commons/python/utils.py
commons/smtp/__init__.py
commons/smtp/objects.py
commons/smtp/smtp.py
commons/static/commons/conf/browserconfig.xml
commons/static/commons/conf/site.webmanifest
commons/static/commons/css/bootstrap.css
commons/static/commons/css/bootstrap.css.map
commons/static/commons/css/commons.css
commons/static/commons/css/external_commons.css
commons/static/commons/css/internal_commons.css
commons/static/commons/img/favicon.ico
commons/static/commons/js/bootstrap.bundle.min.js
commons/static/commons/js/bootstrap.bundle.min.js.map
commons/static/commons/js/commons.js
commons/static/commons/js/date.utils.js
commons/static/commons/js/external_commons.js
commons/static/commons/js/internal_commons.js
commons/static/commons/js/jquery.min.js
commons/static/commons/js/jquery.min.map
commons/static/commons/js/jquery.utils.js
commons/static/commons/js/modal.utils.js
commons/static/commons/js/utils.js
commons/static/themes/elipse/conf/browserconfig.xml
commons/static/themes/elipse/conf/site.webmanifest
commons/static/themes/elipse/css/elipse.css
commons/static/themes/elipse/css/elipse.css.map
commons/static/themes/elipse/img/favicon.ico
commons/static/themes/elipse/img/favicon.svg
commons/static/themes/elipse/img/logo.svg
commons/static/themes/elipse/js/bootstrap.bundle.min.js
commons/static/themes/elipse/js/elipse.js
commons/static/themes/elipse/js/jquery.min.js
commons/static/themes/onnavas/conf/browserconfig.xml
jnunes_commons.egg-info/PKG-INFO
jnunes_commons.egg-info/SOURCES.txt
jnunes_commons.egg-info/dependency_links.txt
jnunes_commons.egg-info/requires.txt
jnunes_commons.egg-info/top_level.txt