Metadata-Version: 2.1
Name: jnunes-commons
Version: 0.3.19
Summary: Base Application for Django projects
Home-page: https://github.com/jarnunes/commons
Author: Jardel Nunes
Author-email: jarnunesc@gmail.com
License: MIT License
Platform: UNKNOWN
Classifier: Environment :: Web Environment
Classifier: Framework :: Django :: 4.0
Classifier: Intended Audience :: Developers
Classifier: License :: OSI Approved :: MIT License
Classifier: Operating System :: OS Independent
Classifier: Programming Language :: Python :: 3.10
Requires-Python: >=3.0
License-File: LICENSE
